{"data":{"allMagazinesJson":{"edges":[{"node":{"title":"億ラビットマガジン"}},{"node":{"title":"偽ラビットマガジン"}},{"node":{"title":"HACKER's CLUB MAGAZINE"}},{"node":{"title":"test"}},{"node":{"title":"ALIS Analytics"}},{"node":{"title":"test2"}},{"node":{"title":"億ラビットマガジン"}},{"node":{"title":"偽ラビットマガジン"}},{"node":{"title":"test"}},{"node":{"title":"ALIS Analytics"}},{"node":{"title":"test2"}},{"node":{"title":"Voe Rabbit Magazine"}},{"node":{"title":"Voe Rabbit Magazine"}}]}},"pageContext":{"file_id":"admin"}}